odoo/addons/shopinvader_auth_api_key/README.rst
odoo/addons/shopinvader_auth_api_key/__init__.py
odoo/addons/shopinvader_auth_api_key/__manifest__.py
odoo/addons/shopinvader_auth_api_key/components/__init__.py
odoo/addons/shopinvader_auth_api_key/components/service_context_provider.py
odoo/addons/shopinvader_auth_api_key/controllers/__init__.py
odoo/addons/shopinvader_auth_api_key/controllers/main.py
odoo/addons/shopinvader_auth_api_key/demo/auth_api_key_demo.xml
odoo/addons/shopinvader_auth_api_key/demo/shopinvader_backend_demo.xml
odoo/addons/shopinvader_auth_api_key/i18n/shopinvader_auth_api_key.pot
odoo/addons/shopinvader_auth_api_key/models/__init__.py
odoo/addons/shopinvader_auth_api_key/models/shopinvader_backend.py
odoo/addons/shopinvader_auth_api_key/readme/CONTRIBUTORS.rst
odoo/addons/shopinvader_auth_api_key/readme/DESCRIPTION.rst
odoo/addons/shopinvader_auth_api_key/services/__init__.py
odoo/addons/shopinvader_auth_api_key/services/service.py
odoo/addons/shopinvader_auth_api_key/static/description/index.html
odoo/addons/shopinvader_auth_api_key/tests/__init__.py
odoo/addons/shopinvader_auth_api_key/tests/test_controller.py
odoo/addons/shopinvader_auth_api_key/tests/test_shopinvader_backend.py
odoo/addons/shopinvader_auth_api_key/views/shopinvader_backend_view.xml
odoo14_addon_shopinvader_auth_api_key-14.0.1.1.1.dist-info/METADATA
odoo14_addon_shopinvader_auth_api_key-14.0.1.1.1.dist-info/WHEEL
odoo14_addon_shopinvader_auth_api_key-14.0.1.1.1.dist-info/top_level.txt
odoo14_addon_shopinvader_auth_api_key-14.0.1.1.1.dist-info/RECORD
